pyodhean_server/__init__.py
pyodhean_server/api.py
pyodhean_server/app.py
pyodhean_server/auth.py
pyodhean_server/celery.py
pyodhean_server/exceptions.py
pyodhean_server/logger.py
pyodhean_server/settings.py
pyodhean_server/solver/__init__.py
pyodhean_server/solver/resources.py
pyodhean_server/solver/schemas.py
pyodhean_server/solver/task.py
tests/__init__.py
tests/common.py
tests/conftest.py
tests/test_auth.py
tests/test_io_logging.py
tests/test_resources.py
tests/utils.py
pyodhean_server-1.0.0.dist-info/LICENSE
pyodhean_server-1.0.0.dist-info/METADATA
pyodhean_server-1.0.0.dist-info/WHEEL
pyodhean_server-1.0.0.dist-info/top_level.txt
pyodhean_server-1.0.0.dist-info/RECORD
