Metadata-Version: 2.1
Name: pyodhean-server
Version: 1.0.0
Summary: Optimization of District Heating Networks
Home-page: https://github.com/sigopti/pyodhean-server
Author: Nobatek/INEF4
Author-email: jlafrechoux@nobatek.com
License: AGPLv3+
Keywords: District,Heating,Network,Optimization
Platform: UNKNOWN
Classifier: Development Status :: 5 - Production/Stable
Classifier: Intended Audience :: Developers
Classifier: Topic :: Scientific/Engineering
Classifier: License :: OSI Approved :: GNU Affero General Public License v3 or later (AGPLv3+)
Classifier: Programming Language :: Python :: 3.7
Classifier: Programming Language :: Python :: 3.8
Classifier: Programming Language :: Python :: 3.9
Requires-Python: >=3.7
Requires-Dist: pyodhean (>=1.0.0)
Requires-Dist: celery[redis] (<6.0,>=4.4.0)
Requires-Dist: werkzeug (<3,>=2.0)
Requires-Dist: flask (<3,>=2.0)
Requires-Dist: python-dotenv (>=0.9.0)
Requires-Dist: flask-smorest (<0.32,>=0.31.0)
Requires-Dist: marshmallow (<4,>=3.0.0)
Requires-Dist: flask-httpauth (>=4.0.0)
